osfooler_ng/__init__.py
osfooler_ng/module_p0f.py
osfooler_ng/osfooler_ng.py
osfooler_ng/dep/nmap-os-db
osfooler_ng/dep/p0f.fp
osfooler_ng/dep/p0fa.fp
osfooler_ng/dep/p0fr.fp
OSfooler_ng_openwrt-1.1.dist-info/LICENSE.md
OSfooler_ng_openwrt-1.1.dist-info/METADATA
OSfooler_ng_openwrt-1.1.dist-info/WHEEL
OSfooler_ng_openwrt-1.1.dist-info/entry_points.txt
OSfooler_ng_openwrt-1.1.dist-info/top_level.txt
OSfooler_ng_openwrt-1.1.dist-info/RECORD
