Metadata-Version: 2.1
Name: OSfooler-ng-openwrt
Version: 1.1
Summary: OSfooler-ng prevents remote OS active/passive fingerprinting by tools like nmap or p0f. This fork based on change of Python nfqueue (NetfilterQueue) version from 0.5 to 0.8.1 for the sake of run the OSfooler-ng on different distros, not just deb-based.
Home-page: https://github.com/moonbaseDelta/OSfooler-ng
Author: Jaime Sanchez (@segofensiva), moonbaseDelta
Author-email: jsanchez@seguridadofensiva.com
License: UNKNOWN
Platform: UNKNOWN
Classifier: Development Status :: 4 - Beta
Classifier: Environment :: Console
Classifier: Operating System :: POSIX :: Linux
Classifier: Topic :: System :: Networking
Classifier: Programming Language :: Python
Classifier: Topic :: Security
Classifier: License :: OSI Approved :: GNU General Public License v3 (GPLv3)
Requires-Dist: dpkt
Requires-Dist: scapy
